daindex/__init__.py
daindex/core.py
daindex/main.py
daindex/ml.py
daindex/util.py
daindex-0.10.0.dist-info/licenses/LICENSE
daindex-0.10.0.dist-info/METADATA
daindex-0.10.0.dist-info/WHEEL
daindex-0.10.0.dist-info/top_level.txt
daindex-0.10.0.dist-info/RECORD
