Metadata-Version: 2.4
Name: daindex
Version: 0.10.0
Summary: Deterioration Allocation Index Framework
Author-email: Harrison Wilde <h.wilde@ucl.ac.uk>, Honghan Wu <honghan.wu@gmail.com>
License-Expression: MIT
Project-URL: repository, https://github.com/knowlab/daindex
Project-URL: issues, https://github.com/knowlab/daindex/issues
Keywords: evaluation,fairness,machine learning,data science,bias
Classifier: Development Status :: 3 - Alpha
Classifier: Programming Language :: Python :: 3
Classifier: Operating System :: OS Independent
Requires-Python: >=3.10
License-File: LICENSE
Requires-Dist: joblib>=1.5.1
Requires-Dist: matplotlib>=3.10.3
Requires-Dist: numpy>=2.2.6
Requires-Dist: pandas>=2.3.1
Requires-Dist: scikit-learn>=1.7.1
Requires-Dist: seaborn>=0.13.2
Requires-Dist: tqdm>=4.67.1
Dynamic: license-file
